pyquickwebgui/__init__.py
pyquickwebgui/app.py
pyquickwebgui/browser/BaseBrowser.py
pyquickwebgui/browser/CommandBrowser.py
pyquickwebgui/browser/TauriBrowser.py
pyquickwebgui/browser/WebviewBrowser.py
pyquickwebgui/browser/__init__.py
pyquickwebgui/config/QuickConfig.py
pyquickwebgui/config/__init__.py
pyquickwebgui/modules/BaseResponse.py
pyquickwebgui/modules/__init__.py
pyquickwebgui/rootplugins/BasePlugin.py
pyquickwebgui/rootplugins/LogPlugin.py
pyquickwebgui/rootplugins/StrayPlugin.py
pyquickwebgui/rootplugins/WebpyPlugin.py
pyquickwebgui/rootplugins/__init__.py
pyquickwebgui/servers/BaseDefaultServer.py
pyquickwebgui/servers/DefaultServerDjango.py
pyquickwebgui/servers/DefaultServerFastApi.py
pyquickwebgui/servers/DefaultServerFlask.py
pyquickwebgui/servers/DefaultServerFlaskSocketIO.py
pyquickwebgui/servers/DefaultServerWebpy.py
pyquickwebgui/servers/__init__.py
pyquickwebgui-0.1.1.dist-info/LICENSE
pyquickwebgui-0.1.1.dist-info/METADATA
pyquickwebgui-0.1.1.dist-info/WHEEL
pyquickwebgui-0.1.1.dist-info/top_level.txt
pyquickwebgui-0.1.1.dist-info/RECORD
