Metadata-Version: 2.1
Name: pyquickwebgui
Version: 0.1.1
Summary: Create desktop applications with Flask/Django/FastAPI/web.py!
Requires-Python: >=3.8
License-File: LICENSE
Requires-Dist: psutil >=6.0
Requires-Dist: sphinx ==7.1.2
Requires-Dist: uvicorn >=0.33.0
Requires-Dist: waitress >=3.0.0
